{
    "Steam_EResult_0": "Không",
    "Steam_EResult_1": "OK",
    "Steam_EResult_2": "Thất bại",
    "Steam_EResult_3": "Không có kết nối",
    "Steam_EResult_4": "4",
    "Steam_EResult_5": "Mật khẩu không hợp lệ",
    "Steam_EResult_6": "Đã đăng nhập ở nơi khác",
    "Steam_EResult_7": "Phương thức không hợp lệ",
    "Steam_EResult_8": "Tham số không hợp lệ",
    "Steam_EResult_9": "Không tìm thấy file tin",
    "Steam_EResult_10": "Đang bận",
    "Steam_EResult_11": "Trạng thái không hợp lệ",
    "Steam_EResult_12": "Tên không hợp lệ",
    "Steam_EResult_13": "Email không hợp lệ",
    "Steam_EResult_14": "Trùng tên",
    "Steam_EResult_15": "Truy cập bị từ chối",
    "Steam_EResult_16": "Hết thời gian",
    "Steam_EResult_17": "Bị cấm",
    "Steam_EResult_18": "Không tìm thấy tài khoản",
    "Steam_EResult_19": "Steam ID không hợp lệ",
    "Steam_EResult_20": "Dịch vụ không sẵn sàng",
    "Steam_EResult_21": "Chưa đăng nhập",
    "Steam_EResult_22": "Chờ xử lý",
    "Steam_EResult_23": "Mã hóa thất bại",
    "Steam_EResult_24": "Không đủ quyền hạn",
    "Steam_EResult_25": "Đã vượt quá giới hạn",
    "Steam_EResult_26": "Đã thu hồi yêu cầu",
    "Steam_EResult_27": "Giấy phép đã hết hạn",
    "Steam_EResult_28": "Đã quy đổi",
    "Steam_EResult_29": "Yêu cầu bị trùng",
    "Steam_EResult_30": "Đã sở hữu",
    "Steam_EResult_31": "Không tìm thấy địa chỉ IP",
    "Steam_EResult_32": "Persistence thất bại",
    "Steam_EResult_33": "Khóa thất bại",
    "Steam_EResult_34": "Đã thay thế phiên",
    "Steam_EResult_35": "Kết nối thất bại",
    "Steam_EResult_36": "Quá trình handshake không thành công",
    "Steam_EResult_37": "Hoạt động I/O (nhập/xuất) thất bại",
    "Steam_EResult_38": "Mất kết nối bởi Máy chủ từ xa",
    "Steam_EResult_39": "Không tìm thấy giỏ hàng",
    "Steam_EResult_40": "Đã chặn",
    "Steam_EResult_41": "Đã phớt lờ",
    "Steam_EResult_42": "Không trùng khớp",
    "Steam_EResult_43": "Tài khoản bị vô hiệu",
    "Steam_EResult_44": "Dịch vụ chỉ có quyền đọc",
    "Steam_EResult_45": "Tài khoản không đặc trưng",
    "Steam_EResult_46": "Quản trị viên OK",
    "Steam_EResult_47": "Phiên bản nội dung",
    "Steam_EResult_48": "Thử một CM khác",
    "Steam_EResult_49": "Yêu cầu mật khẩu để đuổi phiên",
    "Steam_EResult_50": "Đã đăng nhập ở một nơi khác",
    "Steam_EResult_51": "Đã đình chỉ/tạm hoãn yêu cầu",
    "Steam_EResult_52": "Đã hủy yêu cầu",
    "Steam_EResult_53": "Lỗi dữ liệu bị hỏng hoặc không thể phục hồi",
    "Steam_EResult_54": "Ổ đĩa không đủ dung lượng",
    "Steam_EResult_55": "Gọi từ xa thất bại",
    "Steam_EResult_56": "Chưa đặt mật khẩu",
    "Steam_EResult_57": "Tài khoản ngoài chưa liên kết với tài khoản Steam",
    "Steam_EResult_58": "PSN Ticket không hợp lệ",
    "Steam_EResult_59": "Tài khoản ngoài đã liên kết với tài khoản Steam khác",
    "Steam_EResult_60": "Xung đột file từ xa",
    "Steam_EResult_61": "Mật khẩu trái luật",
    "Steam_EResult_62": "Trùng với giá trị trước đó",
    "Steam_EResult_63": "Đăng nhập tài khoản bị từ chối",
    "Steam_EResult_64": "Không thể sử dụng mật khẩu cũ",
    "Steam_EResult_65": "Mã xác thực đăng nhập không hợp lệ",
    "Steam_EResult_66": "Đăng nhập tài khoản bị từ chối, không có email được gửi",
    "Steam_EResult_67": "Thiết bị phần cứng không có khả năng IPT",
    "Steam_EResult_68": "Lỗi khởi tạo IPT",
    "Steam_EResult_69": "Tiến trình thất bại do giới hạn quản lý trẻ em đối với người dùng hiện tại",
    "Steam_EResult_70": "Truy vấn Facebook báo lỗi",
    "Steam_EResult_71": "Mã xác thực đăng nhập đã hết hạn",
    "Steam_EResult_72": "Hạn chế IP đăng nhập thất bại",
    "Steam_EResult_73": "Tài khoản đã bị khóa",
    "Steam_EResult_74": "Đăng nhập tài khoản bị từ chối, cần xác thực email",
    "Steam_EResult_75": "Không có URL khớp",
    "Steam_EResult_76": "Phản hồi xấu",
    "Steam_EResult_77": "Yêu cầu nhập lại mật khẩu",
    "Steam_EResult_78": "Giá trị nằm ngoài phạm vi",
    "Steam_EResult_79": "Lỗi bất ngờ",
    "Steam_EResult_80": "Tính năng đã vô hiệu",
    "Steam_EResult_81": "Đăng tải CEG không hợp lệ",
    "Steam_EResult_82": "Thiết bị bị hạn chế",
    "Steam_EResult_83": "Bị khóa vùng",
    "Steam_EResult_84": "Vượt quá giới hạn tần suất",
    "Steam_EResult_85": "Đăng nhập tài khoản bị từ chối, cần mã xác thực hai lớp",
    "Steam_EResult_86": "Vật phẩm hoặc danh mục đã bị xóa",
    "Steam_EResult_87": "Có quá nhiều lần thử đăng nhập",
    "Steam_EResult_88": "Mã xác thực hai lớp không khớp",
    "Steam_EResult_89": "Mã kích hoạt hai lớp không khớp",
    "Steam_EResult_90": "Tài khoản gắn liền với nhiều người chơi",
    "Steam_EResult_91": "Chưa điều chỉnh",
    "Steam_EResult_92": "Không có thiết bị di động",
    "Steam_EResult_93": "Thời gian không khớp",
    "Steam_EResult_94": "Mã SMS thất bại",
    "Steam_EResult_95": "Quá nhiều tài khoản truy cập vào tài nguyên này",
    "Steam_EResult_96": "Có quá nhiều thay đổi về tài khoản này",
    "Steam_EResult_97": "Có quá nhiều thay đổi về số điện thoại này",
    "Steam_EResult_98": "Bạn phải hoàn tiền giao dịch này vào ví",
    "Steam_EResult_99": "Gửi email thất bại",
    "Steam_EResult_100": "Đơn hàng chưa thanh toán",
    "Steam_EResult_101": "Cần captcha",
    "Steam_EResult_102": "Token đăng nhập máy chủ trò chơi bị từ chối",
    "Steam_EResult_103": "Người sở hữu token đăng nhập máy chủ trò chơi bị từ chối",
    "Steam_EResult_104": "Loại vật phẩm không hợp lệ",
    "Steam_EResult_105": "Địa chỉ IP bị cấm",
    "Steam_EResult_106": "Token đăng nhập máy chủ trò chơi đã hết hạn",
    "Steam_EResult_107": "Không đủ tiền",
    "Steam_EResult_108": "Quá nhiều tồn đọng",
    "Steam_EResult_109": "Không tìm thấy giấy phép phòng máy",
    "Steam_EResult_110": "Vượt quá giới hạn gửi của mạng",
    "Steam_EResult_111": "Tài khoản không phải bạn bè",
    "Steam_EResult_112": "Tài khoản người dùng bị giới hạn",
    "Login_WaitingForNetwork": "Đang đợi mạng...",
    "Login_WaitingForServer": "Đang đợi máy chủ hồi âm...",
    "Login_ConnectingUser": "Đang kết nối tài khoản Steam:",
    "Login_ShuttingDown": "Đang tắt...",
    "Login_LoggingOut": "Đang đăng xuất...",
    "Login_EnterCredentials": "Nhập thông tin đăng nhập",
    "Login_AccountName": "Tài khoản phòng máy",
    "Login_AccountHelp": "Dùng tài khoản phòng máy bạn vừa tạo dành riêng cho máy chủ tại địa điểm này",
    "Login_Password": "Mật khẩu",
    "Login_Login": "Đăng nhập",
    "Login_RememberPassword": "Nhớ mật khẩu của tôi",
    "Login_EnterSteamGuard": "Mã Steam Guard cho %1$s",
    "Login_EnterTwoFactor": "Nhập mã xác thực hai lớp cho %1$s",
    "Login_StartingOffline": "Steam sẽ bắt đầu chế độ ngắt mạng cho tài khoản %1$s",
    "Login_StayOffline": "Duy trì ngoại tuyến",
    "Login_GoOnline": "Nối mạng",
    "Login_SteamGuardTitle": "Steam Guard - Cần cấp phép cho máy tính",
    "Login_SteamGuardDesc": "Để tăng cường bảo mật, bạn sẽ cần cấp quyền truy cập cho máy tính này bằng cách nhập mã đặc biệt mà chúng tôi mới gửi đến địa chỉ email của bạn.",
    "Login_TwoFactorTitle": "Yêu cầu xác thực hai lớp",
    "Login_TwoFactorDesc": "Để tăng cường bảo mật, bạn sẽ cần cấp quyền truy cập cho máy tính này bằng cách nhập mã Steam Guard từ ứng dụng xác thực trên di động của bạn.",
    "Login_LastError": "Đăng nhập thất bại: %1$s",
    "Login_TwoFactorMismatch": "Mã xác thực hai lớp không trùng khớp",
    "Login_PasswordMismatch": "Bạn đã nhập sai mật khẩu hoặc tên tài khoản. Vui lòng kiểm tra và thử lại.",
    "Logout_Logout": "Đăng xuất",
    "Logout_Exit": "Thoát",
    "Logout_Prompt_ChangeUser": "Khởi động lại máy chủ Steam PC Cafe bằng tài khoản khác?",
    "Logout_Prompt_Exit": "Thoát máy chủ Steam PC Cafe?",
    "Menu_Header_Settings": "Thiết lập",
    "Menu_Language": "Ngôn ngữ",
    "Menu_Cache": "Bộ nhớ tạm nội dung",
    "Menu_ChangeAccount": "Đổi tài khoản",
    "Menu_Exit": "Thoát",
    "Title": "Máy chủ Steam PC Cafe",
    "Button_Restart": "Khởi động lại",
    "Status_SteamService": "Dịch vụ Steam",
    "Status_ContentCache": "Bộ nhớ cache nội dung",
    "Status_Enabled": "Bật",
    "Status_Disabled": "Tắt",
    "Status_Connected": "Đã kết nối",
    "Status_NotConnected": "Chưa kết nối",
    "Status_NoConnection": "Máy chủ đang kết nối lại với các dịch vụ phụ trợ của Steam. Vui lòng chờ.",
    "Status_Retrying": "Thử lại...",
    "Status_NoSteamCmd": "Không thể kết nối với ứng dụng SteamCMD.",
    "Status_NoSteamCmd_Help": "Thử khởi động lại SteamCMD hoặc kiểm tra cổng %1$s đã mở và sẵn sàng sử dụng trên máy tính này.",
    "Status_Error": "Lỗi",
    "Language_Configure": "Thiết lập ngôn ngữ",
    "Cache_Configure": "Thiết lập bộ nhớ cache nội dung",
    "Cache_State": "Trạng thái cache",
    "Cache_Location": "Địa điểm",
    "Cache_Port": "Cổng",
    "Cache_MaxSize": "Dung lượng tối đa",
    "Cache_CurrentSize": "Dung lượng hiện tại",
    "Cache_P2P": "P2P",
    "Cache_Explicit_IP": "Địa chỉ IP rõ ràng",
    "Cache_External_Process": "Sử dụng ứng dụng bên ngoài cho cache",
    "Cache_Bandwidth": "Băng thông hiện tại",
    "Cache_BytesServed": "Tổng số byte đã phục vụ",
    "Cache_EnableCache": "Bật cache",
    "Cache_EnableP2P": "Bật P2P",
    "Cache_RestartRequired": "Việc thay đổi thiết lập sẽ cần khởi động lại.",
    "Cache_UpdateFailed": "Cập nhật thiết lập bộ nhớ cache thất bại. Bạn có thể cài đặt thủ công bằng việc thay đổi trên file steamconsole.cfg.",
    "Cache_LocationTip": "Vị trí của bộ nhớ cache tải trò chơi trên máy chủ",
    "Cache_PortTip": "Việc tải trò chơi của chương trình Steam sẽ được proxy qua cổng này trên máy chủ phòng máy",
    "Cache_MaxSizeTip": "Dung lượng tối đa trên đĩa dành cho bộ nhớ đệm tải trò chơi",
    "Cache_P2PTip": "Đánh dấu không bắt buộc, cho phép các chương trình Steam trong hệ thống của bạn chia sẻ dữ liệu tải với nhau, giúp giảm lưu lượng",
    "Cache_ExplicitIPTip": "Thiết lập này chép đè lên địa chỉ IP bộ nhớ cache nội dung",
    "Cache_ExternalProcessTip": "Bật tính năng này nếu cache nội dung sẽ được xử lý thông qua ứng dụng bên ngoài, chẳng hạn như ứng dụng cache cho Linux theo proxy",
    "ClientStatus_Title": "Kết nối chương trình Steam",
    "ClientStatus_Connections": "Các chương trình đã kết nối %1$s",
    "ClientStatus_IPAddress": "Địa chỉ IP",
    "ClientStatus_Hostname": "Tên máy chủ",
    "ClientStatus_Status": "Tình trạng",
    "ClientStatus_NoClients": "Không tìm thấy chương trình Steam nào trên mạng này.",
    "ClientStatus_Troubleshoot": "Làm theo hướng dẫn sau để cài đặt máy chủ của bạn",
    "ClientStatus_Troubleshoot1": "Đảm bảo rằng máy chủ phòng máy và các chương trình Steam đều đang chạy trên cùng một mạng vật lý, không có bộ định tuyến (router) nào giữa chúng. Máy chủ phát hiện ra các máy trạm thông qua một giao thức phát sóng trên cổng 27036 và 27037 mà bộ định tuyến có thể can thiệp.",
    "ClientStatus_Troubleshoot2": "Đảm bảo hệ thống của bạn đã mở tất cả cổng cần thiết để giao tiếp trên chương trình Steam được chính xác. Để biết thêm chi tiết, hãy truy cập %1$s.",
    "ClientStatus_Action": "Hành động",
    "ClientStatus_Account": "Tài khoản",
    "ClientStatus_Amount": "Số lượng",
    "ClientStatus_Success": "Thành công",
    "ClientStatus_Pending": "Chờ xử lý",
    "ClientStatus_Failed": "Thất bại",
    "ClientStatus_Approve": "Duyệt",
    "ClientStatus_FundingRequests": "Yêu cầu nạp ví",
    "ClientStatus_FundingInstr": "Duyệt cung cấp quỹ ví cho người dùng sau khi bạn nhận thanh toán",
    "AcctStatus_NoLicenses": "Tài khoản này không sở hữu bất cứ giấy phép thương mại nào nên bạn không thể chia sẻ trò chơi. Giấy phép thương mại có thể được mua tại %1$s bằng tài khoản Chủ giấy phép phòng máy.",
    "AcctStatus_NotAssociated": "Tài khoản này hiện không liên kết với phòng máy nào. Để thiết lập phòng máy của bạn, hãy đăng nhập vào tài khoản Chủ giấy phép phòng máy của bạn tại %1$s",
    "AcctStatus_LoggedInElsewhere": "Tài khoản này hiện đang đăng nhập tại một địa điểm khác. Bạn sẽ cần phải đăng xuất máy chủ tại địa điểm đó trước, sau đó mới có thể đăng nhập tại đây.",
    "ForAdditionalInfo": "Để thêm thông tin hoặc thực hiện các thay đổi trên tài khoản, vui lòng đăng nhập vào %1$s bằng tài khoản Chủ giấy phép phòng máy"
}
