<root>
	<styles>
		<include src="file://{resources}/styles/steamstyles.css" />
		<include src="file://{resources}/styles/wizardstyles.css" />
		<include src="file://{resources}/styles/settings.css" />
	</styles>

	<SettingsPanelNetwork_Credentials class="WizardChild" defaultfocus="SettingsNetwork_Credentials" tabindex="auto" selectionpos="auto">
		<!-- top header panel -->
		<Label class="WizardChildTitle" text="#Settings_Network" />

		<Label class="SettingsCallout LongDesc" text="#SettingsNetwork_WAP_Credentials" />
		<Panel class="Spacer"/>

		<Panel id="CustomSSID_Edit" class="NetworkWiFiCredentials FlowDown" >
			<TextEntry
				id="SettingsNetwork_Credentials"
				class="WizardTextEntry"
				textinputid="Credentials"
				textinputdoneactionstring="#SettingsNetwork_Credentials_C"
				textinputclass="HalfWidth DockRight AppearFromBottomCenter NoSuggest"
			/>
			<Panel class="Spacer"/>
			<Panel class="HorzContainer">
				<ToggleButton class="CheckBox" id="ShowPasswordToggle" onactivate="ShowPasswordToggled()" />
				<Label id="ShowPasswordLabel" class="LongDesc" text="#SettingsNetwork_ShowPassword" />
			</Panel>
		</Panel>

		<Panel id="WizardButtons">
			<Button class="WizardButton GapRight" id="ButtonNext" onactivate="WizardButtonNext()" selectionpos="0,2">
				<Label id="Label" text="#WizardButton_Next" />
			</Button>

			<Button class="WizardButton GapRight" id="ButtonBack" onactivate="WizardButtonBack()" selectionpos="20,2">
				<Label id="Label" text="#WizardButton_Back" />
			</Button>

			<Button class="WizardButton GapRight" id="ButtonCancel" onactivate="WizardButtonCancel()" selectionpos="30,2" >
				<Label id="Label" text="#WizardButton_Cancel" />
			</Button>
		</Panel>

	</SettingsPanelNetwork_Credentials>

</root>
