<root>
	<styles>		
		<include src="file://{resources}/styles/steamstyles.css"/>
		<include src="file://{resources}/styles/welcometosteam.css" />
		<include src="file://{resources}/styles/mainmenu.css" />
	</styles>

	<WelcomeToSteamIndividualTip selectionpos="auto" mousecanactivate="unfocused">
	   <Button class="SubPanel TouchButton" tabindex="1" selectionpos="0,1" onactivate="None();" >
	   		<Label class="SubDesc" id="sub_touchmenu_left" text="#MainMenu_Welcome_Controller_Update_TouchMenu_Description2" />
	   		<Panel class="TouchMenuFlow"> 
				<Panel id="HR4" class="HR" />
				<Panel class="SubPanelCenterContainer">
					<Image class="SubImageCenterAlign" src="file://{images}/welcomeupdates/controller_update_gyro_touchmenu.jpg" scaling="stretch-to-fit-x-preserve-aspect" />	
					<Panel class="SubText" id ="sub_touchmenu_right"> 
						<Label class="SubHeader" id="sub_align_right" text="#MainMenu_Welcome_Controller_Update_TouchMenu_Header" />
						<Label class="SubDesc" text="#MainMenu_Welcome_Controller_Update_TouchMenu_Description" />
					</Panel>
				</Panel>
			</Panel>
		</Button>
  </WelcomeToSteamIndividualTip>
</root>