<root>
	<styles>
		<include src="file://{resources}/styles/steamstyles.css" />
		<include src="file://{resources}/styles/store/checkout.css" />
	</styles>
	
	<CheckoutPaymentMethodFields defaultfocus="PaymentMethod">
		<Label class="PaymentMethodHeader" id="PaymentMethodHeader" text="#Checkout_PaymentMethod_Instructions" />
		<DropDown id="PaymentMethod" />					
		<Panel class="HorizontalRule" />

		<Panel id="CreditCardFields">
			<Label class="PaymentMethodHeader" text="#Checkout_PaymentMethod_CartNumber" />
			<TextEntry id="CreditCardNumber" maxchars="16" 
				textinputid="CheckoutFormTextEntry"
				textinputclass="HalfWidth DockRight AppearFromBottomCenter"
				textmode="numeric"
				textinputdoneactionstring="#UI_Next"
				oninputsubmit="NavigateToNextField();"
			/>
			<Label class="PaymentMethodHeader" text="#Checkout_PaymentMethod_ExpirationDate" />
			<Panel class="CreditCardExpirationRow">
				<DropDown id="CreditCardMonth" oninputsubmit="NavigateToNextField();">
					<Label id="CreditCardMonthNotSet" text="--" />
					<Label id="CreditCardMonth1" text="01" />
					<Label id="CreditCardMonth2" text="02" />
					<Label id="CreditCardMonth3" text="03" />
					<Label id="CreditCardMonth4" text="04" />
					<Label id="CreditCardMonth5" text="05" />
					<Label id="CreditCardMonth6" text="06" />
					<Label id="CreditCardMonth7" text="07" />
					<Label id="CreditCardMonth8" text="08" />
					<Label id="CreditCardMonth9" text="09" />
					<Label id="CreditCardMonth10" text="10" />
					<Label id="CreditCardMonth11" text="11" />
					<Label id="CreditCardMonth12" text="12" />
				</DropDown>
				<DropDown id="CreditCardYear" oninputsubmit="NavigateToNextField();">
					<Label id="CreditCardYearNotSet" text="--" />
				</DropDown>
			</Panel>
			<Label class="PaymentMethodHeader" text="#Checkout_PaymentMethod_SecurityCode" />
			<TextEntry id="CreditCardSecurityCode" maxchars="4"
				textinputid="CheckoutFormTextEntry"
				textinputclass="HalfWidth DockRight AppearFromBottomCenter"
				textmode="numeric"
				textinputdoneactionstring="#UI_Next"
				oninputsubmit="NavigateToNextField();"
			/>
		</Panel>	
			
		<Panel id="UpdatePayPalFields">
			<Label text="#Checkout_PaymentMethod_UpdatePayPal" />
		</Panel>
		<Panel id="PayPalFields">
			<Label text="#Checkout_PaymentMethod_PayPalInstructions" />
		</Panel>
		<Panel id="PayPalSavedFields">
			<Label text="#Checkout_PaymentMethod_PayPalSaved" />
		</Panel>
		<Panel id="SteamAccountFields">
			<Label id="WalletLow" text="#Checkout_PaymentMethod_WalletLow" />
		</Panel>
		<Panel id="UpdateBankNameFields">
			<Label class="PaymentMethodHeader" text="#Checkout_PaymentMethod_BankName" />
			<DropDown id="BankName" oninputsubmit="NavigateToNextField();"/>
		</Panel>			
		<Panel id="NoPaymentDataFields">
			<ToggleButton id="LiveInCountryNoBilling" class="CheckBox" text="#Checkout_PaymentMethod_VerifyCountry" />
		</Panel>
		<ToggleButton id="SavePaymentInfo" class="CheckBox" selected="true" text="#Checkout_PaymentMethod_SaveInfo" />
		<Label id="ContainsRecurringSubscription" visible="false" text="#Checkout_PaymentMethod_ContainsRecurringSubscription" />
	</CheckoutPaymentMethodFields>	
</root>
